shower/User.gif
shower/__init__.py
shower/bgm.ogg
shower/helper.py
shower/logo.gif
shower/title.png
shower/颜色表.png
shower/img/--.png
shower/img/-o.png
shower/img/x-.png
shower/img/xo.png
shower/img/music/pause.png
shower/img/music/play.png
shower-0.2.20210306.dist-info/METADATA
shower-0.2.20210306.dist-info/WHEEL
shower-0.2.20210306.dist-info/top_level.txt
shower-0.2.20210306.dist-info/RECORD
